{
  "pt-BR": {
    "nav": {
      "home": "Início",
      "features": "Recursos",
      "pricing": "Preços",
      "login": "Entrar",
      "signup": "Cadastrar",
      "dashboard": "Painel"
    },
    "hero": {
      "headline": "Transforme seu fluxo de trabalho com inteligência",
      "subheadline": "A plataforma tudo-em-um para otimizar sua produtividade e escalar seu negócio.",
      "cta_primary": "Começar Gratuitamente",
      "cta_secondary": "Ver Demonstração",
      "new_badge": "Novo",
      "productivity": "Produtividade",
      "time_saved": "Tempo Economizado",
      "trust_label": "Mais de 1.000 usuários confiam na Lumina Flow"
    },
    "features": {
      "title": "Recursos Poderosos",
      "subtitle": "Tudo o que você precisa para ter sucesso",
      "feature_1_title": "Automação Inteligente",
      "feature_1_desc": "Automatize tarefas repetitivas e foque no que realmente importa.",
      "feature_1_tag": "Geração de orçamentos",
      "feature_2_title": "Análise em Tempo Real",
      "feature_2_desc": "Acompanhe todos os orçamentos gerados e organize clientes e valores.",
      "feature_2_tag": "Histórico de orçamentos",
      "feature_3_title": "Mais contratos",
      "feature_3_desc": "Propostas profissionais aumentam significativamente sua taxa de vendas.",
      "feature_3_tag": "Alta conversão de vendas",
      "feature_4_title": "Experiência do Cliente",
      "feature_4_desc": "Orçamentos organizados, informações claras e processo transparente.",
      "feature_4_tag": "Mais profissionalismo"
    },
    "impact": {
      "title": "Mais velocidade e profissionalismo para prestadores de serviços",
      "subtitle": "Mapeie seus orçamentos, acompanhe os status e crie novos orçamentos em um só lugar, oferecendo uma experiência premium aos clientes.",
      "card_automation_title": "Mapeie seus orçamentos",
      "card_automation_desc": "Veja todo o histórico de orçamentos que você já gerou no sistema.",
      "card_visibility_title": "Acompanhe os status",
      "card_visibility_desc": "Aceite, recuse ou edite rapidamente os orçamentos enviados aos clientes.",
      "card_security_title": "Crie novos orçamentos",
      "card_security_desc": "Crie propostas profissionais, variadas e prontas em poucos minutos.",
      "cta_compare": "Comparar planos",
      "cta_flow": "Ver fluxo na prática"
    },
    "workflow": {
      "title": "Um fluxo moderno em quatro etapas",
      "subtitle": "Crie um orçamento em poucos segundos",
      "step_1_title": "Crie um novo orçamento",
      "step_1_desc": "Comece um orçamento com poucos cliques no sistema.",
      "step_2_title": "Escolha entre vários templates",
      "step_2_desc": "Selecione entre diferentes layouts prontos para acelerar o envio.",
      "step_3_title": "Compartilhe com clientes",
      "step_3_desc": "Envie o link público, imagem ou PDF para aprovação em segundos.",
      "step_4_title": "Seja mais profissional e produtivo",
      "step_4_desc": "Encante clientes com orçamentos bem projetados e entregues rapidamente."
    },
    "testimonials": {
      "title": "Histórias reais de equipes de alta performance",
      "subtitle": "Veja como empresas e prestadores de diferentes setores usam a Lumina Flow",
      "quote_1": "Antes perdíamos muito tempo montando proposta manual no Word. Agora geramos propostas em menos de 2 minutos e aumentamos em 30% a taxa de fechamento.",
      "author_1_role": "CEO, Agência de Marketing Digital — PixelBoost",
      "quote_2": "Passei a enviar orçamentos organizados e claros. Parei de perder clientes por falta de profissionalismo.",
      "author_2_role": "Eletricista Autônomo",
      "quote_3": "Escolho o tipo de serviço e o orçamento sai pronto. Parece algo de empresa grande, mas uso sozinho.",
      "author_3_role": "Designer Freelancer"
    },
    "cta": {
      "title": "Pronto para transformar seu fluxo de trabalho?",
      "subtitle": "Junte-se a centenas de usuários que já estão usando a Lumina Flow.",
      "cta_primary": "Começar Gratuitamente"
    },
    "pricing": {
      "title": "Planos Flexíveis",
      "subtitle": "Escolha o plano ideal para você",
      "monthly": "Mensal",
      "annual": "Anual",
      "save": "Economize 20%",
      "free_plan": "Grátis",
      "basic_plan": "Basic",
      "pro_plan": "Pro",
      "enterprise_plan": "Enterprise",
      "per_month": "/mês",
      "per_year": "/ano",
      "current_plan": "Plano Atual",
      "popular": "Mais Popular",
      "feature_included": "Incluído",
      "feature_not_included": "Não incluído",
      "billing_monthly": "Cobrança mensal",
      "billing_annual": "Cobrança anual",
      "free_feat_1": "3 orçamentos",
      "free_feat_2": "20 templates customizados",
      "free_feat_3": "Suporte para dúvidas",
      "basic_feat_1": "Orçamentos ilimitados",
      "basic_feat_2": "Templates premium desbloqueados",
      "basic_feat_3": "Acesso ao gerenciamento de orçamentos",
      "basic_feat_4": "Suporte prioritário",
      "pro_contact_plan": "Pro",
      "pro_contact_desc": "Customizações exclusivas, integrações dedicadas e acompanhamento consultivo.",
      "pro_contact_feat_1": "Implantação guiada pela nossa equipe",
      "pro_contact_feat_2": "Acesso ao sistema para criar novos templates",
      "pro_contact_feat_3": "Suporte prioritário 24h",
      "pro_contact_feat_4": "Fluxos automáticos exclusivos",
      "pro_contact_cta": "Fale Conosco",
      "pro_feat_1": "Orçamentos ilimitados",
      "pro_feat_2": "Análise avançada",
      "pro_feat_3": "Suporte prioritário",
      "pro_feat_4": "Acesso à API",
      "ent_feat_1": "Tudo do Pro",
      "ent_feat_2": "Integrações personalizadas",
      "ent_feat_3": "Suporte dedicado",
      "ent_feat_4": "Garantia SLA"
    },
    "auth": {
      "login_title": "Bem-vindo de volta",
      "login_subtitle": "Entre na sua conta para continuar",
      "signup_title": "Crie sua conta",
      "signup_subtitle": "Comece sua jornada conosco",
      "full_name": "Nome Completo",
      "email": "E-mail",
      "password": "Senha",
      "confirm_password": "Confirmar Senha",
      "remember_me": "Lembrar-me",
      "forgot_password": "Esqueceu a senha?",
      "no_account": "Não tem uma conta?",
      "has_account": "Já tem uma conta?",
      "create_account": "Criar conta",
      "sign_in": "Entrar",
      "or_continue_with": "Ou continue com",
      "google": "Google",
      "email_placeholder": "seu@email.com",
      "password_placeholder": "Sua senha",
      "reset_modal_title_request": "Recuperar senha",
      "reset_modal_title_change": "Definir nova senha",
      "reset_modal_request_description": "Informe o e-mail cadastrado para receber o link de redefinição.",
      "reset_modal_change_description": "Defina uma nova senha para acessar sua conta.",
      "reset_modal_email_label": "E-mail",
      "reset_modal_send_link": "Enviar link",
      "reset_modal_close": "Fechar",
      "reset_modal_new_password": "Nova senha",
      "reset_modal_confirm_password": "Confirmar nova senha",
      "reset_modal_update_password": "Atualizar senha",
      "reset_modal_request_new_link": "Solicitar novo link",
      "reset_modal_back_to_login": "Voltar ao login",
      "reset_modal_status_sending": "Enviando instruções...",
      "reset_modal_status_email_sent": "Se o e-mail existir, você receberá as instruções em instantes.",
      "reset_modal_status_email_error": "Não foi possível enviar o e-mail de recuperação.",
      "reset_modal_status_unexpected_error": "Erro inesperado. Tente novamente.",
      "reset_modal_error_invalid_email": "Informe um e-mail válido.",
      "reset_modal_error_min_length": "A senha deve conter ao menos 8 caracteres.",
      "reset_modal_error_mismatch": "As senhas informadas não são iguais.",
      "reset_modal_error_invalid_link": "Link de redefinição inválido. Solicite um novo.",
      "reset_modal_status_updating": "Atualizando senha...",
      "reset_modal_status_success": "Senha atualizada com sucesso. Faça login novamente.",
      "reset_modal_status_reset_error": "Não foi possível redefinir a senha.",
      "reset_modal_status_prompt_new_password": "Crie uma nova senha com pelo menos 8 caracteres.",
      "reset_modal_close_aria": "Fechar modal",
      "verification_title": "Verifique seu e-mail",
      "verification_subtitle": "Enviamos um código de verificação para seu e-mail",
      "verification_message": "Por favor, verifique sua caixa de entrada e clique no link de verificação para ativar sua conta.",
      "resend_code": "Reenviar código",
      "change_email": "Alterar e-mail",
      "back_to_login": "Voltar ao",
      "new_email": "Novo E-mail",
      "update_email": "Atualizar e-mail",
      "cancel": "Cancelar",
      "change_email_title": "Alterar e-mail",
      "change_email_subtitle": "Digite um novo endereço de e-mail"
    },
    "dashboard": {
      "welcome": "Bem-vindo",
      "overview": "Painel",
      "subscription": "Assinatura",
      "subscription_status": "Status",
      "subscription_active": "Ativa",
      "subscription_inactive": "Inativa",
      "subscription_trial": "Teste",
      "plan_type": "Plano",
      "next_billing": "Próxima Cobrança",
      "cancel_subscription": "Cancelar",
      "upgrade_plan": "Fazer Upgrade",
      "settings": "Configurações",
      "logout": "Sair",
      "quotations": "Orçamentos",
      "new_quotation": "Novo Orçamento",
      "quotation_history": "Histórico de Orçamentos",
      "generate_pdf": "Gerar PDF",
      "view_details": "Ver Detalhes",
      "client_name": "Nome do Cliente",
      "client_email": "Email do Cliente",
      "service_description": "Descrição do Serviço",
      "notes": "Observações",
      "discount": "Desconto",
      "value": "Valor",
      "expiry_date": "Data de Validade",
      "generate": "Gerar",
      "save": "Salvar",
      "cancel": "Cancelar",
      "status": "Status",
      "filter_all": "Todos",
      "filter_pending": "Pendentes",
      "filter_accepted": "Aceitos",
      "filter_rejected": "Recusados",
      "filter_expired": "Expirados",
      "pending": "Pendente",
      "accepted": "Aceito",
      "rejected": "Recusado",
      "expired": "Expirado",
      "date": "Data",
      "actions": "Ações",
      "free_limit": "Limite Gratuito: 3 orçamentos",
      "upgrade_cta": "Upgrade para Basic (ilimitado)",
      "no_quotations": "Nenhum orçamento ainda",
      "start_quotation": "Crie seu primeiro orçamento",
      "profile": "Perfil",
      "edit_profile": "Editar Perfil",
      "your_name": "Seu Nome",
      "company_name": "Nome da Empresa",
      "total_quotations": "Total",
      "complete_profile": "Preencha o seu perfil para desbloquear todos os recursos",
      "add_photo": "Coloque uma foto de perfil/logotipo empresa",
      "add_whatsapp": "Adicione seu número do WhatsApp",
      "fill_profile": "Preencher Perfil",
      "client_info": "Informações do Cliente",
      "service_info": "Informações do Serviço",
      "select_template": "Selecione um Template",
      "template_modern": "Moderno",
      "template_modern_desc": "Design limpo e minimalista",
      "template_classic": "Clássico",
      "template_classic_desc": "Estilo tradicional profissional",
      "template_bold": "Negrito",
      "template_bold_desc": "Destaque visual forte",
      "history_subtitle": "Gerencie todos os seus orçamentos",
      "share": "Compartilhar",
      "create_new_quotation_card_title": "Criar Novo Orçamento",
      "select_quotation_type_description": "Escolha o tipo de orçamento que deseja criar",
      "create_quotation_button": "Criar Orçamento",
      "upgrade_title": "Upgrade para Basic",
      "upgrade_subtitle": "Desbloqueie recursos ilimitados",
      "edit_profile_subtitle": "Atualize suas informações para deixar sua conta completa",
      "upload_photo": "Carregar Foto",
      "photo_hint": "A imagem será comprimida automaticamente",
      "cancel_plan": "Cancelar plano",
      "cancel_plan_note": "Ao cancelar, você manterá o acesso até o fim do ciclo atual e não será cobrado novamente.",
      "next_billing_label": "Próxima cobrança:",
      "upgrade_badge": "Plano Basic",
      "upgrade_card_title": "Desbloqueie o melhor da Lumina Flow",
      "upgrade_card_subtitle": "Aumente seus limites, ganhe suporte prioritário e recursos avançados para enviar propostas em segundos.",
      "upgrade_benefit_unlimited": "Orçamentos ilimitados e aprovados sem restrições.",
      "upgrade_benefit_branding": "Templates premium com a identidade da sua marca.",
      "upgrade_benefit_priority": "Suporte prioritário e notificações em tempo real.",
      "upgrade_now": "Fazer upgrade agora",
      "current_plan": "Plano Atual",
      "free_plan_note": "Você está no plano gratuito. Faça upgrade para desbloquear recursos ilimitados.",
      "plan_summary_badge": "Seu plano",
      "plan_summary_text": "Gerencie sua assinatura e desbloqueie recursos avançados.",
      "plan_pro": "Plano Pro",
      "plan_basic": "Plano Basic",
      "plan_free": "Plano Gratuito",
      "cancel_anytime": "Cancele quando quiser.",
      "contact_support_to_cancel": "Entre em contato com o suporte para gerenciar sua assinatura.",
      "reactivate_quotation": "Ativar Orçamento",
      "new_expiry_date": "Nova Data de Validade",
      "reactivate": "Ativar",
      "edit_quotation": "Editar Orçamento",
      "share_quotation": "Compartilhar Orçamento",
      "copy_link": "Copiar Link",
      "download_image": "Baixar Imagem",
      "download_pdf": "Baixar PDF",
      "share_apps": "Compartilhar",
      "history_tab_history": "Histórico",
      "history_tab_results": "Resultados",
      "history_tab_hint": "Em breve você poderá alternar entre histórico e resultados.",
      "history_tab_hint_active": "Acompanhe o histórico ou visualize resultados detalhados.",
      "history_results_hint": "Visualize o desempenho geral dos seus orçamentos.",
      "history_results_title": "Resultados de Orçamentos",
      "history_results_subtitle": "Acompanhe métricas consolidadas e desempenho financeiro",
      "history_results_total": "Total de orçamentos",
      "history_results_overview_title": "Visão Geral",
      "history_results_overview_desc": "Resumo rápido da quantidade de orçamentos por status e taxa de conversão.",
      "history_results_total_accepted": "Total aceitos",
      "history_results_total_pending": "Total pendentes",
      "history_results_total_rejected": "Total recusados",
      "history_results_total_expired": "Total expirados",
      "history_results_conversion": "Taxa de conversão",
      "history_results_conversion_hint": "Percentual de orçamentos aceitos.",
      "history_results_finance_title": "Resultados Financeiros",
      "history_results_finance_desc": "Valores consolidados por moeda com base no status do orçamento.",
      "history_results_generated": "Valor total gerado",
      "history_results_closed": "Valor total fechado",
      "history_results_lost": "Valor perdido",
      "history_results_additional_currencies_title": "Outras moedas",
      "history_results_generated_short": "Gerado",
      "history_results_closed_short": "Fechado",
      "history_results_lost_short": "Perdido",
      "history_results_empty_title": "Nenhum dado disponível ainda",
      "history_results_empty_desc": "Crie orçamentos para visualizar seus resultados consolidados aqui.",
      "create_quotation_subtitle": "Crie seu orçamento em poucos passos",
      "quotation_quick": "Orçamento Rápido",
      "quotation_quick_desc": "Ideal para orçamentos simples e rápidos",
      "quotation_detailed": "Orçamento Detalhado",
      "quotation_detailed_desc": "Para orçamentos complexos com múltiplos itens",
      "phone": "Telefone",
      "phone_address": "Telefone e Endereço",
      "multiple_items": "Múltiplos itens",
      "auto_calculated": "Valor calculado automaticamente",
      "address": "Endereço",
      "items": "Itens do Orçamento",
      "description": "Descrição",
      "qty": "Qtd",
      "subtotal": "Subtotal",
      "add_item": "Adicionar Item",
      "notes_placeholder": "Observações adicionais",
      "layout_palette": "Paleta do layout",
      "template_colors": "Cores do template {name}",
      "palette_unavailable": "Paleta não disponível",
      "palette_hint": "Cores que compõem este orçamento.",
      "cancellation_scheduled_title": "Cancelamento agendado",
      "cancellation_scheduled_message": "Seu plano foi cancelado e ficará ativo até {date}.",
      "payment_failed_title": "Pagamento não processado",
      "payment_failed_message": "Não conseguimos processar seu pagamento. Atualize sua forma de pagamento para evitar a perda de acesso ao plano.",
      "update_payment_button": "Atualizar forma de pagamento",
      "subscription_canceled_title": "Plano cancelado",
      "subscription_canceled_message": "Seu plano foi cancelado.",
      "reactivate_plan": "Reativar plano",
      "cancellation_scheduled_card_message": "Seu plano ficará ativo até",
      "cancellation_scheduled_card_after": "Após essa data, você perderá o acesso aos recursos ilimitados.",
      "subscription_canceled_card_message": "Seu plano foi cancelado. Faça upgrade para voltar a usar recursos ilimitados.",
      "payment_pending_title": "Pagamento pendente",
      "payment_pending_message": "Não conseguimos processar seu pagamento. Atualize sua forma de pagamento para evitar a perda de acesso ao plano."
    },
    "common": {
      "loading": "Carregando...",
      "loading_helper": "Aguarde um momento, estamos processando sua solicitação.",
      "error": "Ocorreu um erro",
      "success": "Sucesso",
      "cancel": "Cancelar",
      "save": "Salvar",
      "delete": "Excluir",
      "edit": "Editar",
      "close": "Fechar",
      "submit": "Enviar",
      "back": "Voltar",
      "next": "Próximo",
      "previous": "Anterior",
      "select": "Selecionar",
      "yes": "Sim",
      "no": "Não",
      "search": "Buscar",
      "filter": "Filtrar",
      "sort": "Ordenar",
      "view_all": "Ver todos",
      "learn_more": "Saiba mais",
      "get_started": "Começar",
      "contact_us": "Fale Conosco",
      "privacy_policy": "Política de Privacidade",
      "terms_of_service": "Termos de Serviço",
      "theme": "Tema"
    },
    "modal": {
      "choose_language": "Selecione seu idioma",
      "portuguese": "Português",
      "english": "English"
    },
    "currency": {
      "symbol": "R$",
      "code": "BRL"
    }
  },
  "en-GB": {
    "nav": {
      "home": "Home",
      "features": "Features",
      "pricing": "Pricing",
      "login": "Login",
      "signup": "Sign Up",
      "dashboard": "Dashboard"
    },
    "hero": {
      "headline": "Transform your workflow with intelligence",
      "subheadline": "The all-in-one platform to optimise your productivity and scale your business.",
      "cta_primary": "Start for Free",
      "cta_secondary": "View Demo",
      "new_badge": "New",
      "productivity": "Productivity",
      "time_saved": "Time Saved",
      "trust_label": "Trusted by 1,000+ users worldwide"
    },
    "features": {
      "title": "Powerful Features",
      "subtitle": "Everything you need to succeed",
      "feature_1_title": "Smart Automation",
      "feature_1_desc": "Automate repetitive tasks so you can focus on delivery.",
      "feature_1_tag": "Quotation generation",
      "feature_2_title": "Real-time Analytics",
      "feature_2_desc": "Track every quotation you send and organise clients and values.",
      "feature_2_tag": "Quotation history",
      "feature_3_title": "Win more contracts",
      "feature_3_desc": "Professional proposals dramatically increase close rates.",
      "feature_3_tag": "High conversion",
      "feature_4_title": "Client Experience",
      "feature_4_desc": "Transparent budgets with clear information in one place.",
      "feature_4_tag": "More professionalism"
    },
    "impact": {
      "title": "More speed and polish for service providers",
      "subtitle": "Map every quote, track statuses and create new proposals in one place.",
      "card_automation_title": "Map your quotes",
      "card_automation_desc": "See the full history of every estimate you ever sent.",
      "card_visibility_title": "Track statuses",
      "card_visibility_desc": "Approve, reject or edit quotes in a couple of taps.",
      "card_security_title": "Create new quotes",
      "card_security_desc": "Spin up professional proposals with multiple layouts in minutes.",
      "cta_compare": "Compare plans",
      "cta_flow": "See the workflow"
    },
    "workflow": {
      "title": "A modern four-step workflow",
      "subtitle": "Create a quotation in seconds",
      "step_1_title": "Create a new quotation",
      "step_1_desc": "Start a proposal with only a few clicks.",
      "step_2_title": "Pick from multiple templates",
      "step_2_desc": "Select the layout that best matches your service.",
      "step_3_title": "Share with clients",
      "step_3_desc": "Send a public link or download as image/PDF.",
      "step_4_title": "Look professional and stay fast",
      "step_4_desc": "Deliver well-designed quotes that impress clients."
    },
    "testimonials": {
      "title": "Real stories from high-performing teams",
      "subtitle": "See how companies and contractors rely on Lumina Flow",
      "quote_1": "We went from editing proposals in Word to sending polished quotes in two minutes and grew our close rate by ~30%.",
      "author_1_role": "CEO, Digital Marketing Agency — PixelBoost",
      "quote_2": "Having organised quotes with clear pricing stopped me from losing clients due to lack of professionalism.",
      "author_2_role": "Independent Electrician",
      "quote_3": "I just pick the service type and the quote is ready. It feels enterprise-grade even though I work solo.",
      "author_3_role": "Freelance Designer"
    },
    "cta": {
      "title": "Ready to transform your workflow?",
      "subtitle": "Join hundreds of users already on Lumina Flow.",
      "cta_primary": "Start for Free"
    },
    "pricing": {
      "title": "Flexible Plans",
      "subtitle": "Choose the perfect plan for you",
      "monthly": "Monthly",
      "annual": "Annual",
      "save": "Save 20%",
      "free_plan": "Free",
      "basic_plan": "Basic",
      "pro_plan": "Pro",
      "enterprise_plan": "Enterprise",
      "per_month": "/month",
      "per_year": "/year",
      "current_plan": "Current Plan",
      "popular": "Most Popular",
      "feature_included": "Included",
      "feature_not_included": "Not included",
      "billing_monthly": "Monthly billing",
      "billing_annual": "Annual billing",
      "free_feat_1": "3 quotations",
      "free_feat_2": "20 custom templates",
      "free_feat_3": "Question support",
      "basic_feat_1": "Unlimited quotations",
      "basic_feat_2": "Premium templates unlocked",
      "basic_feat_3": "Quotation management access",
      "basic_feat_4": "Priority support",
      "pro_contact_plan": "Pro",
      "pro_contact_desc": "Exclusive customisations, dedicated integrations and strategic follow-up.",
      "pro_contact_feat_1": "Guided deployment with our team",
      "pro_contact_feat_2": "Template creation system access",
      "pro_contact_feat_3": "24/7 priority support",
      "pro_contact_feat_4": "Exclusive automated workflows",
      "pro_contact_cta": "Talk to us",
      "pro_feat_1": "Unlimited quotations",
      "pro_feat_2": "Advanced analytics",
      "pro_feat_3": "Priority support",
      "pro_feat_4": "API access",
      "ent_feat_1": "Everything in Pro",
      "ent_feat_2": "Custom integrations",
      "ent_feat_3": "Dedicated support",
      "ent_feat_4": "SLA guarantee"
    },
    "auth": {
      "login_title": "Welcome back",
      "login_subtitle": "Sign in to your account to continue",
      "signup_title": "Create your account",
      "full_name": "Full Name",
      "signup_subtitle": "Start your journey with us",
      "email": "Email",
      "password": "Password",
      "confirm_password": "Confirm Password",
      "remember_me": "Remember me",
      "forgot_password": "Forgot password?",
      "no_account": "Don't have an account?",
      "has_account": "Already have an account?",
      "create_account": "Create account",
      "sign_in": "Sign in",
      "or_continue_with": "Or continue with",
      "google": "Google",
      "email_placeholder": "your@email.com",
      "password_placeholder": "Your password",
      "reset_modal_title_request": "Recover password",
      "reset_modal_title_change": "Set a new password",
      "reset_modal_request_description": "Enter your registered email to receive the reset link.",
      "reset_modal_change_description": "Choose a new password to access your account.",
      "reset_modal_email_label": "Email",
      "reset_modal_send_link": "Send link",
      "reset_modal_close": "Close",
      "reset_modal_new_password": "New password",
      "reset_modal_confirm_password": "Confirm new password",
      "reset_modal_update_password": "Update password",
      "reset_modal_request_new_link": "Request a new link",
      "reset_modal_back_to_login": "Back to login",
      "reset_modal_status_sending": "Sending instructions...",
      "reset_modal_status_email_sent": "If the email exists, you'll receive instructions shortly.",
      "reset_modal_status_email_error": "We couldn't send the recovery email.",
      "reset_modal_status_unexpected_error": "Unexpected error. Please try again.",
      "reset_modal_error_invalid_email": "Please enter a valid email.",
      "reset_modal_error_min_length": "Password must be at least 8 characters.",
      "reset_modal_error_mismatch": "Passwords do not match.",
      "reset_modal_error_invalid_link": "Invalid reset link. Request a new one.",
      "reset_modal_status_updating": "Updating password...",
      "reset_modal_status_success": "Password updated successfully. Please sign in again.",
      "reset_modal_status_reset_error": "We could not reset your password.",
      "reset_modal_status_prompt_new_password": "Create a new password with at least 8 characters.",
      "reset_modal_close_aria": "Close modal",
      "verification_title": "Verify your email",
      "verification_subtitle": "We sent a verification code to your email",
      "verification_message": "Please check your inbox and click the verification link to activate your account.",
      "resend_code": "Resend code",
      "change_email": "Change email",
      "back_to_login": "Back to",
      "new_email": "New Email",
      "update_email": "Update email",
      "cancel": "Cancel",
      "change_email_title": "Change email",
      "change_email_subtitle": "Enter a new email address"
    },
    "dashboard": {
      "welcome": "Welcome",
      "overview": "Dashboard",
      "subscription": "Subscription",
      "subscription_status": "Status",
      "subscription_active": "Active",
      "subscription_inactive": "Inactive",
      "subscription_trial": "Trial",
      "plan_type": "Plan",
      "next_billing": "Next Billing",
      "cancel_subscription": "Cancel",
      "upgrade_plan": "Upgrade",
      "settings": "Settings",
      "logout": "Logout",
      "quotations": "Quotations",
      "new_quotation": "New Quotation",
      "quotation_history": "Quotation History",
      "generate_pdf": "Generate PDF",
      "view_details": "View Details",
      "client_name": "Client Name",
      "client_email": "Client Email",
      "service_description": "Service Description",
      "notes": "Notes",
      "discount": "Discount",
      "value": "Value",
      "expiry_date": "Expiry Date",
      "generate": "Generate",
      "save": "Save",
      "cancel": "Cancel",
      "status": "Status",
      "filter_all": "All",
      "filter_pending": "Pending",
      "filter_accepted": "Accepted",
      "filter_rejected": "Rejected",
      "filter_expired": "Expired",
      "pending": "Pending",
      "accepted": "Accepted",
      "rejected": "Rejected",
      "expired": "Expired",
      "date": "Date",
      "actions": "Actions",
      "free_limit": "Free limit: 3 quotations",
      "upgrade_cta": "Upgrade to Basic (unlimited)",
      "no_quotations": "No quotations yet",
      "start_quotation": "Create your first quotation",
      "profile": "Profile",
      "edit_profile": "Edit Profile",
      "your_name": "Your Name",
      "company_name": "Company Name",
      "total_quotations": "Total",
      "complete_profile": "Complete your profile to unlock all features",
      "add_photo": "Add a profile photo/company logo",
      "add_whatsapp": "Add your WhatsApp number",
      "fill_profile": "Fill Profile",
      "client_info": "Client Information",
      "service_info": "Service Information",
      "select_template": "Select a Template",
      "template_modern": "Modern",
      "template_modern_desc": "Clean and minimalist design",
      "template_classic": "Classic",
      "template_classic_desc": "Traditional professional style",
      "template_bold": "Bold",
      "template_bold_desc": "Strong visual impact",
      "history_subtitle": "Manage all your quotations",
      "share": "Share",
      "create_new_quotation_card_title": "Create New Quotation",
      "select_quotation_type_description": "Choose the quotation type you want to create",
      "create_quotation_button": "Create Quotation",
      "upgrade_title": "Upgrade to Basic",
      "upgrade_subtitle": "Unlock unlimited features",
      "edit_profile_subtitle": "Update your information to keep your account complete",
      "upload_photo": "Upload Photo",
      "photo_hint": "The image will be compressed automatically",
      "cancel_plan": "Cancel plan",
      "cancel_plan_note": "When you cancel, you keep access until the end of the current cycle and will not be charged again.",
      "next_billing_label": "Next billing:",
      "upgrade_badge": "Basic Plan",
      "upgrade_card_title": "Unlock the best of Lumina Flow",
      "upgrade_card_subtitle": "Increase your limits, get priority support and advanced features to send proposals in seconds.",
      "upgrade_benefit_unlimited": "Unlimited, approval-ready quotations without restrictions.",
      "upgrade_benefit_branding": "Premium templates with your brand identity.",
      "upgrade_benefit_priority": "Priority support and real-time notifications.",
      "upgrade_now": "Upgrade now",
      "current_plan": "Current plan",
      "free_plan_note": "You are on the free plan. Upgrade to unlock unlimited features.",
      "plan_summary_badge": "Your plan",
      "plan_summary_text": "Manage your subscription and unlock advanced features.",
      "plan_pro": "Pro Plan",
      "plan_basic": "Basic Plan",
      "plan_free": "Free Plan",
      "cancel_anytime": "Cancel anytime.",
      "contact_support_to_cancel": "Contact support to manage your subscription.",
      "reactivate_quotation": "Reactivate Quotation",
      "new_expiry_date": "New Expiry Date",
      "reactivate": "Reactivate",
      "edit_quotation": "Edit Quotation",
      "share_quotation": "Share Quotation",
      "copy_link": "Copy Link",
      "download_image": "Download Image",
      "download_pdf": "Download PDF",
      "share_apps": "Share",
      "history_tab_history": "History",
      "history_tab_results": "Results",
      "history_tab_hint": "Soon you will be able to switch between history and results.",
      "history_tab_hint_active": "Track your history or explore detailed results.",
      "history_results_hint": "See your overall quotation performance.",
      "history_results_title": "Quotation Results",
      "history_results_subtitle": "Monitor consolidated metrics and financial performance",
      "history_results_total": "Total quotations",
      "history_results_overview_title": "Overview",
      "history_results_overview_desc": "Quick summary of quotation counts by status and conversion rate.",
      "history_results_total_accepted": "Total accepted",
      "history_results_total_pending": "Total pending",
      "history_results_total_rejected": "Total rejected",
      "history_results_total_expired": "Total expired",
      "history_results_conversion": "Conversion rate",
      "history_results_conversion_hint": "Percentage of quotations accepted.",
      "history_results_finance_title": "Financial Results",
      "history_results_finance_desc": "Consolidated amounts by currency based on quotation status.",
      "history_results_generated": "Total generated value",
      "history_results_closed": "Total closed value",
      "history_results_lost": "Lost value",
      "history_results_additional_currencies_title": "Other currencies",
      "history_results_generated_short": "Generated",
      "history_results_closed_short": "Closed",
      "history_results_lost_short": "Lost",
      "history_results_empty_title": "No data available yet",
      "history_results_empty_desc": "Create quotations to view your consolidated results here.",
      "create_quotation_subtitle": "Create your quotation in a few steps",
      "quotation_quick": "Quick Quotation",
      "quotation_quick_desc": "Ideal for simple and quick quotations",
      "quotation_detailed": "Detailed Quotation",
      "quotation_detailed_desc": "For complex quotations with multiple items",
      "phone": "Phone",
      "phone_address": "Phone and Address",
      "multiple_items": "Multiple items",
      "auto_calculated": "Automatically calculated value",
      "address": "Address",
      "items": "Quotation Items",
      "description": "Description",
      "qty": "Qty",
      "subtotal": "Subtotal",
      "add_item": "Add Item",
      "notes_placeholder": "Additional notes",
      "layout_palette": "Layout palette",
      "template_colors": "Template colors for {name}",
      "palette_unavailable": "Palette unavailable",
      "palette_hint": "Colors that make up this quotation.",
      "cancellation_scheduled_title": "Cancellation scheduled",
      "cancellation_scheduled_message": "Your plan has been cancelled and will remain active until {date}.",
      "payment_failed_title": "Payment not processed",
      "payment_failed_message": "We couldn't process your payment. Update your payment method to avoid losing access to your plan.",
      "update_payment_button": "Update payment method",
      "subscription_canceled_title": "Plan cancelled",
      "subscription_canceled_message": "Your plan has been cancelled.",
      "reactivate_plan": "Reactivate plan",
      "cancellation_scheduled_card_message": "Your plan will remain active until",
      "cancellation_scheduled_card_after": "After this date, you will lose access to unlimited resources.",
      "subscription_canceled_card_message": "Your plan has been cancelled. Upgrade to regain access to unlimited resources.",
      "payment_pending_title": "Payment pending",
      "payment_pending_message": "We couldn't process your payment. Update your payment method to avoid losing access to your plan."
    },
    "common": {
      "loading": "Loading...",
      "loading_helper": "Please wait while we process your request.",
      "error": "An error occurred",
      "success": "Success",
      "cancel": "Cancel",
      "save": "Save",
      "delete": "Delete",
      "edit": "Edit",
      "close": "Close",
      "submit": "Submit",
      "back": "Back",
      "next": "Next",
      "previous": "Previous",
      "select": "Select",
      "yes": "Yes",
      "no": "No",
      "search": "Search",
      "filter": "Filter",
      "sort": "Sort",
      "view_all": "View all",
      "learn_more": "Learn more",
      "get_started": "Get started",
      "contact_us": "Contact Us",
      "privacy_policy": "Privacy Policy",
      "terms_of_service": "Terms of Service",
      "theme": "Theme"
    },
    "modal": {
      "choose_language": "Choose your language",
      "portuguese": "Português",
      "english": "English"
    },
    "currency": {
      "symbol": "£",
      "code": "GBP"
    }
  }
}
